dio.py
hello.py
joseph.py
jotaro.py
jojo_hsg-0.1.dist-info/LICENSE.txt
jojo_hsg-0.1.dist-info/METADATA
jojo_hsg-0.1.dist-info/WHEEL
jojo_hsg-0.1.dist-info/top_level.txt
jojo_hsg-0.1.dist-info/RECORD
