Metadata-Version: 2.1
Name: jojo-hsg
Version: 0.1
Summary: Welcome Stand Users
Home-page: https://github.com/harisriguhan-facetagr/jojo
Author: Harisriguhan Sivakumar
Author-email: harisriguhan.s@facetagr.com
License: LICENSE.txt
Platform: UNKNOWN
Classifier: Programming Language :: Python :: 3
Classifier: Programming Language :: Python :: 2
Classifier: License :: OSI Approved :: MIT License
Classifier: Operating System :: OS Independent
Requires-Python: >=2.7
Requires-Dist: setuptools (>=45.2.0)
Provides-Extra: dev
Requires-Dist: pytest (>=3.7) ; extra == 'dev'
